grygry/.DS_Store
grygry/__init__.py
grygry/grycli.py
grygry/lib/.DS_Store
grygry/lib/__init__.py
grygry/lib/grylib.py
grygry/lib/parameters.json
grygry-2.10.0.dist-info/WHEEL
grygry-2.10.0.dist-info/entry_points.txt
grygry-2.10.0.dist-info/METADATA
grygry-2.10.0.dist-info/RECORD
