Metadata-Version: 2.4
Name: grygry
Version: 2.10.0
Summary: Command line utility to grep different types of source code
Keywords: code,source,grep
Author: Jérôme Dumonteil
Author-email: Jérôme Dumonteil <jerome.dumonteil@gmail.com>
License-Expression: MIT
Classifier: Development Status :: 5 - Production/Stable
Classifier: Environment :: Console
Classifier: Intended Audience :: Developers
Classifier: License :: OSI Approved :: MIT License
Classifier: Programming Language :: Python :: 3.10
Classifier: Programming Language :: Python :: 3.11
Classifier: Programming Language :: Python :: 3.12
Classifier: Programming Language :: Python :: 3.13
Classifier: Programming Language :: Python :: 3.14
Classifier: Operating System :: OS Independent
Classifier: Topic :: Text Processing
Classifier: Topic :: Software Development
Requires-Python: >=3.10, <4
Project-URL: Homepage, https://github.com/jdum/grygry
Project-URL: Repository, https://github.com/jdum/grygry
